{"id":"eb259606-7a18-4618-8cca-a3f810fe8af3","revision":0,"last_node_id":522,"last_link_id":1026,"nodes":[{"id":52,"type":"ReduxAdvanced","pos":[890.7469482421875,212.62640380859375],"size":[407.8997497558594,234],"flags":{"collapsed":false},"order":44,"mode":0,"inputs":[{"label":"conditioning","localized_name":"conditioning","name":"conditioning","type":"CONDITIONING","link":1001},{"label":"style_model","localized_name":"style_model","name":"style_model","type":"STYLE_MODEL","link":838},{"label":"clip_vision","localized_name":"clip_vision","name":"clip_vision","type":"CLIP_VISION","link":840},{"label":"image","localized_name":"image","name":"image","type":"IMAGE","link":152},{"label":"mask","localized_name":"mask","name":"mask","shape":7,"type":"MASK"},{"label":"downsampling_factor","localized_name":"downsampling_factor","name":"downsampling_factor","type":"FLOAT","widget":{"name":"downsampling_factor"}},{"label":"downsampling_function","localized_name":"downsampling_function","name":"downsampling_function","type":"COMBO","widget":{"name":"downsampling_function"}},{"label":"mode","localized_name":"mode","name":"mode","type":"COMBO","widget":{"name":"mode"}},{"label":"weight","localized_name":"weight","name":"weight","type":"FLOAT","widget":{"name":"weight"}},{"label":"autocrop_margin","localized_name":"autocrop_margin","name":"autocrop_margin","shape":7,"type":"FLOAT","widget":{"name":"autocrop_margin"}}],"outputs":[{"label":"CONDITIONING","localized_name":"CONDITIONING","name":"CONDITIONING","type":"CONDITIONING","slot_index":0,"links":[73]},{"label":"IMAGE","localized_name":"IMAGE","name":"IMAGE","type":"IMAGE"},{"label":"MASK","localized_name":"MASK","name":"MASK","type":"MASK"}],"properties":{"aux_id":"kaibioinfo/ComfyUI_AdvancedRefluxControl","ver":"2b95c2c866399ca1914b4da486fe52808f7a9c60","Node name for S&R":"ReduxAdvanced","cnr_id":"ComfyUI_AdvancedRefluxControl","widget_ue_connectable":{}},"widgets_values":[2,"area","keep aspect ratio",1,0.1]},{"id":22,"type":"BasicGuider","pos":[1321.630126953125,225.77627563476562],"size":[274.9738464355469,46],"flags":{"collapsed":false},"order":45,"mode":0,"inputs":[{"label":"model","localized_name":"model","name":"model","type":"MODEL","link":122},{"label":"conditioning","localized_name":"conditioning","name":"conditioning","type":"CONDITIONING","link":73}],"outputs":[{"label":"GUIDER","localized_name":"GUIDER","name":"GUIDER","type":"GUIDER","slot_index":0,"links":[30]}],"properties":{"cnr_id":"comfy-core","ver":"0.3.62","Node name for S&R":"BasicGuider","widget_ue_connectable":{}},"widgets_values":[]},{"id":13,"type":"SamplerCustomAdvanced","pos":[1626.313720703125,-180.18438720703125],"size":[299.17071533203125,106],"flags":{"collapsed":false},"order":46,"mode":0,"inputs":[{"label":"noise","localized_name":"noise","name":"noise","type":"NOISE","link":37},{"label":"guider","localized_name":"guider","name":"guider","type":"GUIDER","link":30},{"label":"sampler","localized_name":"sampler","name":"sampler","type":"SAMPLER","link":19},{"label":"sigmas","localized_name":"sigmas","name":"sigmas","type":"SIGMAS","link":20},{"label":"latent_image","localized_name":"latent_image","name":"latent_image","type":"LATENT","link":23}],"outputs":[{"label":"output","localized_name":"output","name":"output","type":"LATENT","slot_index":0,"links":[24]},{"label":"denoised_output","localized_name":"denoised_output","name":"denoised_output","type":"LATENT"}],"properties":{"cnr_id":"comfy-core","ver":"0.3.62","Node name for S&R":"SamplerCustomAdvanced","widget_ue_connectable":{}},"widgets_values":[]},{"id":89,"type":"PreviewImage","pos":[-422.1995849609375,-200.13821411132812],"size":[227.56141662597656,396.97393798828125],"flags":{},"order":36,"mode":0,"inputs":[{"label":"images","localized_name":"images","name":"images","type":"IMAGE","link":126}],"outputs":[],"properties":{"cnr_id":"comfy-core","ver":"0.3.62","Node name for S&R":"PreviewImage","widget_ue_connectable":{}},"widgets_values":[]},{"id":90,"type":"SEGSPreview","pos":[-179.73486328125,-200.39291381835938],"size":[214.18133544921875,392.0643005371094],"flags":{},"order":39,"mode":0,"inputs":[{"label":"segs","localized_name":"segs","name":"segs","type":"SEGS","link":127},{"label":"fallback_image_opt","localized_name":"fallback_image_opt","name":"fallback_image_opt","shape":7,"type":"IMAGE","link":154},{"label":"alpha_mode","localized_name":"alpha_mode","name":"alpha_mode","type":"BOOLEAN","widget":{"name":"alpha_mode"}},{"label":"min_alpha","localized_name":"min_alpha","name":"min_alpha","type":"FLOAT","widget":{"name":"min_alpha"}}],"outputs":[{"label":"IMAGE","localized_name":"IMAGE","name":"IMAGE","shape":6,"type":"IMAGE","slot_index":0,"links":[131]}],"properties":{"aux_id":"ltdrdata/ComfyUI-Impact-Pack","ver":"8.23.0","Node name for S&R":"SEGSPreview","cnr_id":"comfyui-impact-pack","widget_ue_connectable":{}},"widgets_values":[true,1]},{"id":88,"type":"MaskToSEGS","pos":[-423.7891845703125,248.32827758789062],"size":[458.83642578125,170.7250518798828],"flags":{},"order":37,"mode":0,"inputs":[{"label":"mask","localized_name":"mask","name":"mask","type":"MASK","link":125},{"label":"combined","localized_name":"combined","name":"combined","type":"BOOLEAN","widget":{"name":"combined"}},{"label":"crop_factor","localized_name":"crop_factor","name":"crop_factor","type":"FLOAT","widget":{"name":"crop_factor"}},{"label":"bbox_fill","localized_name":"bbox_fill","name":"bbox_fill","type":"BOOLEAN","widget":{"name":"bbox_fill"}},{"label":"drop_size","localized_name":"drop_size","name":"drop_size","type":"INT","widget":{"name":"drop_size"}},{"label":"contour_fill","localized_name":"contour_fill","name":"contour_fill","type":"BOOLEAN","widget":{"name":"contour_fill"}}],"outputs":[{"label":"SEGS","localized_name":"SEGS","name":"SEGS","type":"SEGS","slot_index":0,"links":[127]}],"properties":{"aux_id":"ltdrdata/ComfyUI-Impact-Pack","ver":"8.23.0","Node name for S&R":"MaskToSEGS","cnr_id":"comfyui-impact-pack","widget_ue_connectable":{}},"widgets_values":[false,1.2000000000000002,false,100,false]},{"id":86,"type":"ApplyPulidFlux","pos":[46.02385330200195,210.1507568359375],"size":[225.54238891601562,226],"flags":{},"order":41,"mode":0,"inputs":[{"label":"model","localized_name":"model","name":"model","type":"MODEL","link":833},{"label":"pulid_flux","localized_name":"pulid_flux","name":"pulid_flux","type":"PULIDFLUX","link":834},{"label":"eva_clip","localized_name":"eva_clip","name":"eva_clip","type":"EVA_CLIP","link":119},{"label":"face_analysis","localized_name":"face_analysis","name":"face_analysis","type":"FACEANALYSIS","link":120},{"label":"image","localized_name":"image","name":"image","type":"IMAGE","link":131},{"label":"attn_mask","localized_name":"attn_mask","name":"attn_mask","shape":7,"type":"MASK"},{"label":"options","localized_name":"options","name":"options","shape":7,"type":"OPTIONS"},{"label":"weight","localized_name":"weight","name":"weight","type":"FLOAT","widget":{"name":"weight"}},{"label":"start_at","localized_name":"start_at","name":"start_at","type":"FLOAT","widget":{"name":"start_at"}},{"label":"end_at","localized_name":"end_at","name":"end_at","type":"FLOAT","widget":{"name":"end_at"}}],"outputs":[{"label":"MODEL","localized_name":"MODEL","name":"MODEL","type":"MODEL","slot_index":0,"links":[122,136]}],"properties":{"aux_id":"KY-2000/ComfyUI_PuLID_Flux_ll_FaceNet","ver":"ecd975b3839d6708d27d506ebe943b0b7b674add","Node name for S&R":"ApplyPulidFlux","widget_ue_connectable":{}},"widgets_values":[1.0000000000000002,0,1]},{"id":306,"type":"easy cleanGpuUsed","pos":[1754.75,104.71923065185547],"size":[157.38925170898438,26],"flags":{},"order":48,"mode":0,"inputs":[{"label":"anything","localized_name":"anything","name":"anything","type":"*","link":532}],"outputs":[{"label":"output","localized_name":"output","name":"output","type":"*","links":[533]}],"properties":{"aux_id":"yolain/ComfyUI-Easy-Use","ver":"1.3.3","Node name for S&R":"easy cleanGpuUsed","cnr_id":"comfyui-easy-use","widget_ue_connectable":{}},"widgets_values":[]},{"id":12,"type":"UNETLoader","pos":[-3227.13330078125,-375.16156005859375],"size":[301.06671142578125,94.33255767822266],"flags":{"collapsed":false},"order":0,"mode":0,"inputs":[{"label":"unet_name","localized_name":"unet_name","name":"unet_name","type":"COMBO","widget":{"name":"unet_name"}},{"label":"weight_dtype","localized_name":"weight_dtype","name":"weight_dtype","type":"COMBO","widget":{"name":"weight_dtype"}}],"outputs":[{"label":"MODEL","localized_name":"MODEL","name":"MODEL","type":"MODEL","slot_index":0,"links":[167]}],"properties":{"cnr_id":"comfy-core","ver":"0.3.62","Node name for S&R":"UNETLoader","widget_ue_connectable":{}},"widgets_values":["flux1-dev-fp8.safetensors","fp8_e4m3fn"]},{"id":8,"type":"VAEDecode","pos":[1627.055419921875,-13.054256439208984],"size":[300.3552551269531,49.040958404541016],"flags":{"collapsed":false},"order":47,"mode":0,"inputs":[{"label":"samples","localized_name":"samples","name":"samples","type":"LATENT","link":24},{"label":"vae","localized_name":"vae","name":"vae","type":"VAE","link":839}],"outputs":[{"label":"IMAGE","localized_name":"IMAGE","name":"IMAGE","type":"IMAGE","slot_index":0,"links":[532,798]}],"properties":{"cnr_id":"comfy-core","ver":"0.3.62","Node name for S&R":"VAEDecode","widget_ue_connectable":{}},"widgets_values":[]},{"id":68,"type":"LoraLoader","pos":[-1817.369873046875,-292.26611328125],"size":[415.1219177246094,127.6588363647461],"flags":{"collapsed":false},"order":25,"mode":0,"inputs":[{"label":"model","localized_name":"model","name":"model","type":"MODEL","link":167},{"label":"clip","localized_name":"clip","name":"clip","type":"CLIP","link":166},{"label":"lora_name","localized_name":"lora_name","name":"lora_name","type":"COMBO","widget":{"name":"lora_name"}},{"label":"strength_model","localized_name":"strength_model","name":"strength_model","type":"FLOAT","widget":{"name":"strength_model"}},{"label":"strength_clip","localized_name":"strength_clip","name":"strength_clip","type":"FLOAT","widget":{"name":"strength_clip"}}],"outputs":[{"label":"MODEL","localized_name":"MODEL","name":"MODEL","type":"MODEL","slot_index":0,"links":[94]},{"label":"CLIP","localized_name":"CLIP","name":"CLIP","type":"CLIP","slot_index":1,"links":[95]}],"properties":{"cnr_id":"comfy-core","ver":"0.3.62","Node name for S&R":"LoraLoader","widget_ue_connectable":{}},"widgets_values":["Q版风格V2.0.safetensors",0.8000000000000002,0.25]},{"id":30,"type":"LoraLoader","pos":[-1813.63916015625,-117.22286987304688],"size":[415.1219177246094,127.6588363647461],"flags":{"collapsed":false},"order":31,"mode":0,"inputs":[{"label":"model","localized_name":"model","name":"model","type":"MODEL","link":94},{"label":"clip","localized_name":"clip","name":"clip","type":"CLIP","link":95},{"label":"lora_name","localized_name":"lora_name","name":"lora_name","type":"COMBO","widget":{"name":"lora_name"}},{"label":"strength_model","localized_name":"strength_model","name":"strength_model","type":"FLOAT","widget":{"name":"strength_model"}},{"label":"strength_clip","localized_name":"strength_clip","name":"strength_clip","type":"FLOAT","widget":{"name":"strength_clip"}}],"outputs":[{"label":"MODEL","localized_name":"MODEL","name":"MODEL","type":"MODEL","slot_index":0,"links":[823]},{"label":"CLIP","localized_name":"CLIP","name":"CLIP","type":"CLIP","slot_index":1,"links":[824]}],"properties":{"cnr_id":"comfy-core","ver":"0.3.62","Node name for S&R":"LoraLoader","widget_ue_connectable":{}},"widgets_values":["flux-1-lora-flyway-3d-icon-v1-000014.safetensors",0.9,0.9]},{"id":381,"type":"easy setNode","pos":[-1195.0250244140625,307.932861328125],"size":[210,58],"flags":{},"order":24,"mode":0,"inputs":[{"name":"STYLE_MODEL","type":"STYLE_MODEL","link":827}],"outputs":[],"title":"➡️STYLE_MODEL","properties":{"previousName":"STYLE_MODEL"},"widgets_values":["STYLE_MODEL"],"color":"#223"},{"id":380,"type":"easy setNode","pos":[-1196.7823486328125,183.94569396972656],"size":[210,58],"flags":{},"order":26,"mode":0,"inputs":[{"name":"VAE","type":"VAE","link":826}],"outputs":[],"title":"➡️VAE","properties":{"previousName":"VAE"},"widgets_values":["VAE"],"color":"#223"},{"id":395,"type":"easy getNode","pos":[61.92262649536133,-113.48684692382812],"size":[210,58],"flags":{},"order":1,"mode":0,"inputs":[],"outputs":[{"name":"*","type":"*","links":[834]}],"title":"⬅️PuLIDFlux","properties":{},"widgets_values":["PuLIDFlux"],"color":"#223"},{"id":84,"type":"PulidFluxEvaClipLoader","pos":[60.50648880004883,19.78986167907715],"size":[209.52694702148438,26],"flags":{},"order":2,"mode":0,"inputs":[],"outputs":[{"label":"EVA_CLIP","localized_name":"EVA_CLIP","name":"EVA_CLIP","type":"EVA_CLIP","slot_index":0,"links":[119]}],"properties":{"aux_id":"KY-2000/ComfyUI_PuLID_Flux_ll_FaceNet","ver":"ecd975b3839d6708d27d506ebe943b0b7b674add","Node name for S&R":"PulidFluxEvaClipLoader","widget_ue_connectable":{}},"widgets_values":[]},{"id":85,"type":"PulidFluxInsightFaceLoader","pos":[45.93425369262695,96.51859283447266],"size":[229.76815795898438,58],"flags":{},"order":3,"mode":0,"inputs":[{"label":"provider","localized_name":"provider","name":"provider","type":"COMBO","widget":{"name":"provider"}}],"outputs":[{"label":"FACEANALYSIS","localized_name":"FACEANALYSIS","name":"FACEANALYSIS","type":"FACEANALYSIS","slot_index":0,"links":[120]}],"properties":{"aux_id":"KY-2000/ComfyUI_PuLID_Flux_ll_FaceNet","ver":"ecd975b3839d6708d27d506ebe943b0b7b674add","Node name for S&R":"PulidFluxInsightFaceLoader","widget_ue_connectable":{}},"widgets_values":["CPU"]},{"id":387,"type":"easy getNode","pos":[317.0619812011719,254.8336181640625],"size":[210,58],"flags":{},"order":4,"mode":0,"inputs":[],"outputs":[{"name":"*","type":"*","links":[840]}],"title":"⬅️CLIP_VISION","properties":{},"widgets_values":["CLIP_VISION"],"color":"#223"},{"id":388,"type":"easy getNode","pos":[323.5135192871094,367.1421813964844],"size":[210,58],"flags":{},"order":5,"mode":0,"inputs":[],"outputs":[{"name":"*","type":"*","links":[839]}],"title":"⬅️VAE","properties":{},"widgets_values":["VAE"],"color":"#223"},{"id":378,"type":"easy setNode","pos":[-1194.100341796875,-99.8249740600586],"size":[210,58],"flags":{},"order":35,"mode":0,"inputs":[{"name":"CLIP","type":"CLIP","link":824}],"outputs":[],"title":"➡️CLIP","properties":{"previousName":"CLIP"},"widgets_values":["CLIP"],"color":"#223"},{"id":83,"type":"PulidFluxModelLoader","pos":[-3214.8720703125,355.0511474609375],"size":[418.2752380371094,58],"flags":{},"order":6,"mode":0,"inputs":[{"label":"pulid_file","localized_name":"pulid_file","name":"pulid_file","type":"COMBO","widget":{"name":"pulid_file"}}],"outputs":[{"label":"PULIDFLUX","localized_name":"PULIDFLUX","name":"PULIDFLUX","type":"PULIDFLUX","slot_index":0,"links":[828]}],"properties":{"aux_id":"KY-2000/ComfyUI_PuLID_Flux_ll_FaceNet","ver":"ecd975b3839d6708d27d506ebe943b0b7b674add","Node name for S&R":"PulidFluxModelLoader","widget_ue_connectable":{}},"widgets_values":["pulid_flux_v0.9.1.safetensors"]},{"id":53,"type":"StyleModelLoader","pos":[-3218.49072265625,231.66384887695312],"size":[424.00537109375,58],"flags":{"collapsed":false},"order":7,"mode":0,"inputs":[{"label":"style_model_name","localized_name":"style_model_name","name":"style_model_name","type":"COMBO","widget":{"name":"style_model_name"}}],"outputs":[{"label":"STYLE_MODEL","localized_name":"STYLE_MODEL","name":"STYLE_MODEL","type":"STYLE_MODEL","links":[827]}],"properties":{"cnr_id":"comfy-core","ver":"0.3.62","Node name for S&R":"StyleModelLoader","widget_ue_connectable":{}},"widgets_values":["flux1-redux-dev.safetensors"]},{"id":379,"type":"easy setNode","pos":[-1199.906494140625,69.83032989501953],"size":[210,58],"flags":{},"order":27,"mode":0,"inputs":[{"name":"CLIP_VISION","type":"CLIP_VISION","link":825}],"outputs":[],"title":"➡️CLIP_VISION","properties":{"previousName":"CLIP_VISION"},"widgets_values":["CLIP_VISION"],"color":"#223"},{"id":392,"type":"easy getNode","pos":[-782.8312377929688,-196.15573120117188],"size":[329.98480224609375,58],"flags":{},"order":8,"mode":0,"inputs":[],"outputs":[{"name":"*","type":"*","links":[832]}],"title":"⬅️FL2MODEL","properties":{},"widgets_values":["FL2MODEL"],"color":"#223"},{"id":394,"type":"easy getNode","pos":[58.00697708129883,-209.13919067382812],"size":[210,58],"flags":{},"order":9,"mode":0,"inputs":[],"outputs":[{"name":"*","type":"*","links":[833]}],"title":"⬅️diffusionModel","properties":{},"widgets_values":["diffusionModel"],"color":"#223"},{"id":314,"type":"ImageScaleDownBy","pos":[2072.218505859375,-184.4040069580078],"size":[210,58],"flags":{"collapsed":false},"order":51,"mode":0,"inputs":[{"label":"images","localized_name":"images","name":"images","type":"IMAGE","link":703},{"label":"scale_by","localized_name":"scale_by","name":"scale_by","type":"FLOAT","widget":{"name":"scale_by"}}],"outputs":[{"label":"IMAGE","localized_name":"IMAGE","name":"IMAGE","type":"IMAGE","links":[802]}],"properties":{"aux_id":"sipherxyz/comfyui-art-venture","ver":"1.1.1","Node name for S&R":"ImageScaleDownBy","cnr_id":"comfyui-art-venture","widget_ue_connectable":{}},"widgets_values":[0.5]},{"id":310,"type":"easy cleanGpuUsed","pos":[2296.82080078125,-176.57135009765625],"size":[157.38925170898438,26],"flags":{},"order":53,"mode":0,"inputs":[{"label":"anything","localized_name":"anything","name":"anything","type":"*","link":805}],"outputs":[{"label":"output","localized_name":"output","name":"output","type":"*","links":[]}],"properties":{"aux_id":"yolain/ComfyUI-Easy-Use","ver":"1.3.3","Node name for S&R":"easy cleanGpuUsed","cnr_id":"comfyui-easy-use","widget_ue_connectable":{}},"widgets_values":[]},{"id":371,"type":"easy imageRemBg","pos":[1994.2545166015625,-82.34477233886719],"size":[454.7162170410156,533.8693237304688],"flags":{},"order":52,"mode":0,"inputs":[{"localized_name":"images","name":"images","type":"IMAGE","link":802},{"localized_name":"rem_mode","name":"rem_mode","type":"COMBO","widget":{"name":"rem_mode"},"link":null},{"localized_name":"image_output","name":"image_output","type":"COMBO","widget":{"name":"image_output"},"link":null},{"localized_name":"save_prefix","name":"save_prefix","type":"STRING","widget":{"name":"save_prefix"},"link":null},{"localized_name":"torchscript_jit","name":"torchscript_jit","shape":7,"type":"BOOLEAN","widget":{"name":"torchscript_jit"},"link":null},{"localized_name":"add_background","name":"add_background","shape":7,"type":"COMBO","widget":{"name":"add_background"},"link":null},{"localized_name":"refine_foreground","name":"refine_foreground","shape":7,"type":"BOOLEAN","widget":{"name":"refine_foreground"},"link":null}],"outputs":[{"localized_name":"image","name":"image","type":"IMAGE","links":[805,871]},{"localized_name":"mask","name":"mask","type":"MASK","links":[]}],"properties":{"aux_id":"yolain/ComfyUI-Easy-Use","ver":"1.3.3","Node name for S&R":"easy imageRemBg","cnr_id":"comfyui-easy-use"},"widgets_values":["RMBG-1.4","Preview","ComfyUI",false,"none",false]},{"id":339,"type":"Reroute","pos":[1986.8472900390625,-178.87689208984375],"size":[75,26],"flags":{},"order":49,"mode":0,"inputs":[{"name":"","type":"*","link":798}],"outputs":[{"name":"","type":"IMAGE","links":[703]}],"properties":{"showOutputText":false,"horizontal":false},"color":"#432","bgcolor":"#653"},{"id":5,"type":"EmptyLatentImage","pos":[1317.498291015625,65.7244644165039],"size":[275.6565856933594,106],"flags":{},"order":10,"mode":0,"inputs":[{"label":"width","localized_name":"width","name":"width","type":"INT","widget":{"name":"width"}},{"label":"height","localized_name":"height","name":"height","type":"INT","widget":{"name":"height"}},{"label":"batch_size","localized_name":"batch_size","name":"batch_size","type":"INT","widget":{"name":"batch_size"}}],"outputs":[{"label":"LATENT","localized_name":"LATENT","name":"LATENT","type":"LATENT","slot_index":0,"links":[23]}],"properties":{"cnr_id":"comfy-core","ver":"0.3.62","Node name for S&R":"EmptyLatentImage","widget_ue_connectable":{}},"widgets_values":[768,1024,1]},{"id":406,"type":"SaveImage","pos":[2489.927978515625,-180.8712158203125],"size":[479.7598876953125,629.9290161132812],"flags":{},"order":54,"mode":0,"inputs":[{"localized_name":"images","name":"images","type":"IMAGE","link":871},{"localized_name":"filename_prefix","name":"filename_prefix","type":"STRING","widget":{"name":"filename_prefix"},"link":null}],"outputs":[],"properties":{"cnr_id":"comfy-core","ver":"0.3.59","Node name for S&R":"SaveImage"},"widgets_values":["ComfyUI"]},{"id":11,"type":"DualCLIPLoader","pos":[-3234.9853515625,-217.29942321777344],"size":[315,130],"flags":{"collapsed":false},"order":11,"mode":0,"inputs":[{"label":"clip_name1","localized_name":"clip_name1","name":"clip_name1","type":"COMBO","widget":{"name":"clip_name1"}},{"label":"clip_name2","localized_name":"clip_name2","name":"clip_name2","type":"COMBO","widget":{"name":"clip_name2"}},{"label":"type","localized_name":"type","name":"type","type":"COMBO","widget":{"name":"type"}},{"label":"device","localized_name":"device","name":"device","shape":7,"type":"COMBO","widget":{"name":"device"}}],"outputs":[{"label":"CLIP","localized_name":"CLIP","name":"CLIP","type":"CLIP","slot_index":0,"links":[166]}],"properties":{"cnr_id":"comfy-core","ver":"0.3.62","Node name for S&R":"DualCLIPLoader","widget_ue_connectable":{}},"widgets_values":["flux/t5xxl_fp8_e4m3fn.safetensors","clip_l.safetensors","flux","default"]},{"id":10,"type":"VAELoader","pos":[-3217.772705078125,112.53787994384766],"size":[425.7015075683594,58],"flags":{"collapsed":false},"order":12,"mode":0,"inputs":[{"label":"vae_name","localized_name":"vae_name","name":"vae_name","type":"COMBO","widget":{"name":"vae_name"}}],"outputs":[{"label":"VAE","localized_name":"VAE","name":"VAE","type":"VAE","slot_index":0,"links":[826]}],"properties":{"cnr_id":"comfy-core","ver":"0.3.62","Node name for S&R":"VAELoader","widget_ue_connectable":{}},"widgets_values":["FLUX1/ae.sft"]},{"id":54,"type":"CLIPVisionLoader","pos":[-3224.999755859375,-5.300525188446045],"size":[433.8158264160156,58],"flags":{"collapsed":false},"order":13,"mode":0,"inputs":[{"label":"clip_name","localized_name":"clip_name","name":"clip_name","type":"COMBO","widget":{"name":"clip_name"}}],"outputs":[{"label":"CLIP_VISION","localized_name":"CLIP_VISION","name":"CLIP_VISION","type":"CLIP_VISION","links":[825]}],"properties":{"cnr_id":"comfy-core","ver":"0.3.62","Node name for S&R":"CLIPVisionLoader","widget_ue_connectable":{}},"widgets_values":["sigclip_vision_patch14_384.safetensors"]},{"id":93,"type":"Florence2Run","pos":[-791.2814331054688,-83.14353942871094],"size":[350.20465087890625,489.43865966796875],"flags":{},"order":32,"mode":0,"inputs":[{"label":"image","localized_name":"image","name":"image","type":"IMAGE","link":153},{"label":"florence2_model","localized_name":"florence2_model","name":"florence2_model","type":"FL2MODEL","link":832},{"label":"text_input","localized_name":"text_input","name":"text_input","type":"STRING","widget":{"name":"text_input"}},{"label":"task","localized_name":"task","name":"task","type":"COMBO","widget":{"name":"task"}},{"label":"fill_mask","localized_name":"fill_mask","name":"fill_mask","type":"BOOLEAN","widget":{"name":"fill_mask"}},{"label":"keep_model_loaded","localized_name":"keep_model_loaded","name":"keep_model_loaded","shape":7,"type":"BOOLEAN","widget":{"name":"keep_model_loaded"}},{"label":"max_new_tokens","localized_name":"max_new_tokens","name":"max_new_tokens","shape":7,"type":"INT","widget":{"name":"max_new_tokens"}},{"label":"num_beams","localized_name":"num_beams","name":"num_beams","shape":7,"type":"INT","widget":{"name":"num_beams"}},{"label":"do_sample","localized_name":"do_sample","name":"do_sample","shape":7,"type":"BOOLEAN","widget":{"name":"do_sample"}},{"label":"output_mask_select","localized_name":"output_mask_select","name":"output_mask_select","shape":7,"type":"STRING","widget":{"name":"output_mask_select"}},{"label":"seed","localized_name":"seed","name":"seed","shape":7,"type":"INT","widget":{"name":"seed"}}],"outputs":[{"label":"image","localized_name":"image","name":"image","type":"IMAGE","slot_index":0,"links":[126]},{"label":"mask","localized_name":"mask","name":"mask","type":"MASK","slot_index":1,"links":[125]},{"label":"caption","localized_name":"caption","name":"caption","type":"STRING"},{"label":"data","localized_name":"data","name":"data","type":"JSON"}],"properties":{"aux_id":"kijai/ComfyUI-Florence2","ver":"1.0.6","Node name for S&R":"Florence2Run","cnr_id":"comfyui-florence2","widget_ue_connectable":{}},"widgets_values":["head","caption_to_phrase_grounding",true,false,1024,1,true,"",374141333135024,"fixed"]},{"id":9,"type":"SaveImage","pos":[3143.14892578125,-222.22901916503906],"size":[468.8780212402344,605.09765625],"flags":{"collapsed":false},"order":50,"mode":0,"inputs":[{"label":"images","localized_name":"images","name":"images","type":"IMAGE","link":533},{"label":"filename_prefix","localized_name":"filename_prefix","name":"filename_prefix","type":"STRING","widget":{"name":"filename_prefix"}}],"outputs":[],"properties":{"cnr_id":"comfy-core","ver":"0.3.62","Node name for S&R":"SaveImage","widget_ue_connectable":{}},"widgets_values":["Liblib"]},{"id":398,"type":"easy getNode","pos":[319.0365905761719,21.5297908782959],"size":[210,58],"flags":{},"order":14,"mode":0,"inputs":[],"outputs":[{"name":"*","type":"*","links":[1000]}],"title":"⬅️CLIP","properties":{},"widgets_values":["CLIP"],"color":"#223"},{"id":520,"type":"CLIPTextEncode","pos":[1054.4915771484375,74.03601837158203],"size":[241.1672821044922,88],"flags":{},"order":42,"mode":0,"inputs":[{"localized_name":"clip","name":"clip","type":"CLIP","link":1000},{"localized_name":"text","name":"text","type":"STRING","widget":{"name":"text"},"link":999}],"outputs":[{"localized_name":"CONDITIONING","name":"CONDITIONING","type":"CONDITIONING","links":[1001]}],"properties":{"cnr_id":"comfy-core","ver":"0.3.59","Node name for S&R":"CLIPTextEncode"},"widgets_values":[""]},{"id":519,"type":"easy showAnything","pos":[650.7536010742188,10.148073196411133],"size":[352.0725402832031,156.747314453125],"flags":{},"order":40,"mode":0,"inputs":[{"localized_name":"anything","name":"anything","shape":7,"type":"*","link":998}],"outputs":[{"localized_name":"output","name":"output","type":"*","links":[999]}],"properties":{"aux_id":"yolain/ComfyUI-Easy-Use","ver":"9947b8be70e17ceabafa4fa7f476b54626de4704","Node name for S&R":"easy showAnything"},"widgets_values":["A woman is wearing a blue and white striped shirt and blue jeans. She is holding a baby in her arms. The baby has a yellow shirt on and a pair of white shoes. , masterpiece, best quality,chibi, 3d cartoon style, simple clean white background,highly detailed, plain white background"]},{"id":518,"type":"LayerUtility: TextJoin","pos":[776.0678100585938,-206.48867797851562],"size":[395.42144775390625,130],"flags":{},"order":38,"mode":0,"inputs":[{"label":"text_1","localized_name":"text_1","name":"text_1","type":"STRING","widget":{"name":"text_1"},"link":995},{"label":"text_2","localized_name":"text_2","name":"text_2","shape":7,"type":"STRING","widget":{"name":"text_2"},"link":996},{"label":"text_3","localized_name":"text_3","name":"text_3","shape":7,"type":"STRING","widget":{"name":"text_3"},"link":null},{"label":"text_4","localized_name":"text_4","name":"text_4","shape":7,"type":"STRING","widget":{"name":"text_4"},"link":null}],"outputs":[{"label":"text","localized_name":"text","name":"text","type":"STRING","links":[998]}],"properties":{"aux_id":"chflame163/ComfyUI_LayerStyle","ver":"4f4d5cbbe40e030a5a0bb474fb65c4032585bc3c","Node name for S&R":"LayerUtility: TextJoin"},"widgets_values":["","","",""],"color":"rgba(38, 73, 116, 0.7)"},{"id":399,"type":"LayerUtility: TextBox","pos":[378.81683349609375,-167.0887908935547],"size":[316.0721435546875,91.02921295166016],"flags":{},"order":15,"mode":0,"inputs":[{"localized_name":"text","name":"text","type":"STRING","widget":{"name":"text"},"link":null}],"outputs":[{"localized_name":"text","name":"text","type":"STRING","links":[996]}],"properties":{"aux_id":"chflame163/ComfyUI_LayerStyle","ver":"4f4d5cbbe40e030a5a0bb474fb65c4032585bc3c","Node name for S&R":"LayerUtility: TextBox","cnr_id":"comfyui_layerstyle"},"widgets_values":["masterpiece, best quality,chibi, 3d cartoon style, simple clean white background,highly detailed, plain white background"],"color":"rgba(38, 73, 116, 0.7)"},{"id":92,"type":"Florence2ModelLoader","pos":[-3202.402587890625,737.5348510742188],"size":[412.7292785644531,130],"flags":{},"order":16,"mode":0,"inputs":[{"label":"lora","localized_name":"lora","name":"lora","shape":7,"type":"PEFTLORA"},{"label":"model","localized_name":"model","name":"model","type":"COMBO","widget":{"name":"model"}},{"label":"precision","localized_name":"precision","name":"precision","type":"COMBO","widget":{"name":"precision"}},{"label":"attention","localized_name":"attention","name":"attention","type":"COMBO","widget":{"name":"attention"}},{"label":"convert_to_safetensors","localized_name":"convert_to_safetensors","name":"convert_to_safetensors","shape":7,"type":"BOOLEAN","widget":{"name":"convert_to_safetensors"}}],"outputs":[{"label":"florence2_model","localized_name":"florence2_model","name":"florence2_model","type":"FL2MODEL","slot_index":0,"links":[830]}],"properties":{"aux_id":"kijai/ComfyUI-Florence2","ver":"1.0.6","Node name for S&R":"Florence2ModelLoader","cnr_id":"comfyui-florence2","widget_ue_connectable":{}},"widgets_values":["CogFlorence-2.2-Large","fp16","sdpa",false]},{"id":384,"type":"easy setNode","pos":[-2474.16796875,612.2124633789062],"size":[210,58],"flags":{},"order":28,"mode":0,"inputs":[{"name":"florence2_model","type":"FL2MODEL","link":830}],"outputs":[],"title":"➡️FL2MODEL","properties":{"previousName":"FL2MODEL"},"widgets_values":["FL2MODEL"],"color":"#223"},{"id":521,"type":"easy setNode","pos":[-2698.302490234375,407.7866516113281],"size":[210,58],"flags":{},"order":29,"mode":0,"inputs":[{"name":"florence2_model","type":"FL2MODEL","link":1002}],"outputs":[],"title":"➡️FL2MODEL0","properties":{"previousName":"FL2MODEL0"},"widgets_values":["FL2MODEL0"],"color":"#223"},{"id":510,"type":"DownloadAndLoadFlorence2Model","pos":[-3207.819091796875,507.1647033691406],"size":[318.6021423339844,130],"flags":{},"order":17,"mode":0,"inputs":[{"localized_name":"lora","name":"lora","shape":7,"type":"PEFTLORA","link":null},{"localized_name":"model","name":"model","type":"COMBO","widget":{"name":"model"},"link":null},{"localized_name":"precision","name":"precision","type":"COMBO","widget":{"name":"precision"},"link":null},{"localized_name":"attention","name":"attention","type":"COMBO","widget":{"name":"attention"},"link":null},{"localized_name":"convert_to_safetensors","name":"convert_to_safetensors","shape":7,"type":"BOOLEAN","widget":{"name":"convert_to_safetensors"},"link":null}],"outputs":[{"localized_name":"florence2_model","name":"florence2_model","type":"FL2MODEL","links":[1002]}],"properties":{"aux_id":"kijai/ComfyUI-Florence2","ver":"00b63382966a444a9fefacb65b8deb188d12a458","Node name for S&R":"DownloadAndLoadFlorence2Model"},"widgets_values":["microsoft/Florence-2-large-ft","fp16","sdpa",false]},{"id":389,"type":"easy getNode","pos":[313.5080261230469,126.89259338378906],"size":[210,58],"flags":{},"order":18,"mode":0,"inputs":[],"outputs":[{"name":"*","type":"*","links":[838]}],"title":"⬅️STYLE_MODEL","properties":{},"widgets_values":["STYLE_MODEL"],"color":"#223"},{"id":377,"type":"easy setNode","pos":[-1167.523193359375,-184.25865173339844],"size":[210,60],"flags":{},"order":34,"mode":0,"inputs":[{"name":"MODEL","type":"MODEL","link":823}],"outputs":[],"title":"➡️diffusionModel","properties":{"previousName":"diffusionModel"},"widgets_values":["diffusionModel"],"color":"#223"},{"id":116,"type":"Reroute","pos":[-1298.2896728515625,-253.8816680908203],"size":[75,26],"flags":{},"order":30,"mode":0,"inputs":[{"label":"","name":"","type":"*","link":722}],"outputs":[{"label":"","name":"","type":"IMAGE","links":[152,153,154,987]}],"properties":{"showOutputText":false,"horizontal":false,"widget_ue_connectable":{}}},{"id":522,"type":"easy getNode","pos":[328.0077819824219,-245.66864013671875],"size":[210,58],"flags":{},"order":19,"mode":0,"inputs":[],"outputs":[{"name":"*","type":"*","links":[1003]}],"title":"⬅️FL2MODEL0","properties":{},"widgets_values":["FL2MODEL0"],"color":"#223"},{"id":509,"type":"Florence2Run","pos":[626.6388549804688,-640.6891479492188],"size":[407.09857177734375,364],"flags":{},"order":33,"mode":0,"inputs":[{"localized_name":"image","name":"image","type":"IMAGE","link":987},{"localized_name":"florence2_model","name":"florence2_model","type":"FL2MODEL","link":1003},{"localized_name":"text_input","name":"text_input","type":"STRING","widget":{"name":"text_input"},"link":null},{"localized_name":"task","name":"task","type":"COMBO","widget":{"name":"task"},"link":null},{"localized_name":"fill_mask","name":"fill_mask","type":"BOOLEAN","widget":{"name":"fill_mask"},"link":null},{"localized_name":"keep_model_loaded","name":"keep_model_loaded","shape":7,"type":"BOOLEAN","widget":{"name":"keep_model_loaded"},"link":null},{"localized_name":"max_new_tokens","name":"max_new_tokens","shape":7,"type":"INT","widget":{"name":"max_new_tokens"},"link":null},{"localized_name":"num_beams","name":"num_beams","shape":7,"type":"INT","widget":{"name":"num_beams"},"link":null},{"localized_name":"do_sample","name":"do_sample","shape":7,"type":"BOOLEAN","widget":{"name":"do_sample"},"link":null},{"localized_name":"output_mask_select","name":"output_mask_select","shape":7,"type":"STRING","widget":{"name":"output_mask_select"},"link":null},{"localized_name":"seed","name":"seed","shape":7,"type":"INT","widget":{"name":"seed"},"link":null}],"outputs":[{"localized_name":"image","name":"image","type":"IMAGE","links":null},{"localized_name":"mask","name":"mask","type":"MASK","links":null},{"localized_name":"caption","name":"caption","type":"STRING","links":[995]},{"localized_name":"data","name":"data","type":"JSON","links":null}],"properties":{"aux_id":"kijai/ComfyUI-Florence2","ver":"00b63382966a444a9fefacb65b8deb188d12a458","Node name for S&R":"Florence2Run"},"widgets_values":["","more_detailed_caption",true,false,1024,3,true,"",345821841286995,"randomize"]},{"id":16,"type":"KSamplerSelect","pos":[1313.785888671875,-49.49053192138672],"size":[288.78790283203125,58],"flags":{"collapsed":false},"order":20,"mode":0,"inputs":[{"label":"sampler_name","localized_name":"sampler_name","name":"sampler_name","type":"COMBO","widget":{"name":"sampler_name"}}],"outputs":[{"label":"SAMPLER","localized_name":"SAMPLER","name":"SAMPLER","type":"SAMPLER","links":[19]}],"properties":{"cnr_id":"comfy-core","ver":"0.3.62","Node name for S&R":"KSamplerSelect","widget_ue_connectable":{}},"widgets_values":["dpmpp_2m"]},{"id":17,"type":"BasicScheduler","pos":[1318.327392578125,325.4471435546875],"size":[281.48052978515625,106],"flags":{"collapsed":false},"order":43,"mode":0,"inputs":[{"label":"model","localized_name":"model","name":"model","type":"MODEL","link":136},{"label":"scheduler","localized_name":"scheduler","name":"scheduler","type":"COMBO","widget":{"name":"scheduler"}},{"label":"steps","localized_name":"steps","name":"steps","type":"INT","widget":{"name":"steps"}},{"label":"denoise","localized_name":"denoise","name":"denoise","type":"FLOAT","widget":{"name":"denoise"}}],"outputs":[{"label":"SIGMAS","localized_name":"SIGMAS","name":"SIGMAS","type":"SIGMAS","links":[20]}],"properties":{"cnr_id":"comfy-core","ver":"0.3.62","Node name for S&R":"BasicScheduler","widget_ue_connectable":{}},"widgets_values":["simple",25,1]},{"id":25,"type":"RandomNoise","pos":[1312.457275390625,-186.99244689941406],"size":[291.69061279296875,82.76022338867188],"flags":{"collapsed":false},"order":21,"mode":0,"inputs":[{"label":"noise_seed","localized_name":"noise_seed","name":"noise_seed","type":"INT","widget":{"name":"noise_seed"}}],"outputs":[{"label":"NOISE","localized_name":"NOISE","name":"NOISE","type":"NOISE","links":[37]}],"properties":{"cnr_id":"comfy-core","ver":"0.3.62","Node name for S&R":"RandomNoise","widget_ue_connectable":{}},"widgets_values":[132467095398502,"fixed"]},{"id":39,"type":"LoadImage","pos":[-2583.51611328125,-283.8420104980469],"size":[378.3719177246094,619.8597412109375],"flags":{},"order":22,"mode":0,"inputs":[{"label":"image","localized_name":"image","name":"image","type":"COMBO","widget":{"name":"image"}},{"label":"upload","localized_name":"choose file to upload","name":"upload","type":"IMAGEUPLOAD","widget":{"name":"upload"}}],"outputs":[{"label":"IMAGE","localized_name":"IMAGE","name":"IMAGE","type":"IMAGE","slot_index":0,"links":[722]},{"label":"MASK","localized_name":"MASK","name":"MASK","type":"MASK"}],"properties":{"cnr_id":"comfy-core","ver":"0.3.62","Node name for S&R":"LoadImage","widget_ue_connectable":{}},"widgets_values":["baby2.png","image"]},{"id":382,"type":"easy setNode","pos":[-1211.5994873046875,405.5045166015625],"size":[210,58],"flags":{},"order":23,"mode":0,"inputs":[{"name":"PULIDFLUX","type":"PULIDFLUX","link":828}],"outputs":[],"title":"➡️PuLIDFlux","properties":{"previousName":"PuLIDFlux"},"widgets_values":["PuLIDFlux"],"color":"#223"}],"links":[[19,16,0,13,2,"SAMPLER"],[20,17,0,13,3,"SIGMAS"],[23,5,0,13,4,"LATENT"],[24,13,0,8,0,"LATENT"],[30,22,0,13,1,"GUIDER"],[37,25,0,13,0,"NOISE"],[73,52,0,22,1,"CONDITIONING"],[94,68,0,30,0,"MODEL"],[95,68,1,30,1,"CLIP"],[119,84,0,86,2,"EVA_CLIP"],[120,85,0,86,3,"FACEANALYSIS"],[122,86,0,22,0,"MODEL"],[125,93,1,88,0,"MASK"],[126,93,0,89,0,"IMAGE"],[127,88,0,90,0,"SEGS"],[131,90,0,86,4,"IMAGE"],[136,86,0,17,0,"MODEL"],[152,116,0,52,3,"IMAGE"],[153,116,0,93,0,"IMAGE"],[154,116,0,90,1,"IMAGE"],[166,11,0,68,1,"CLIP"],[167,12,0,68,0,"MODEL"],[532,8,0,306,0,"*"],[533,306,0,9,0,"IMAGE"],[703,339,0,314,0,"IMAGE"],[722,39,0,116,0,"*"],[798,8,0,339,0,"*"],[802,314,0,371,0,"IMAGE"],[805,371,0,310,0,"*"],[823,30,0,377,0,"*"],[824,30,1,378,0,"*"],[825,54,0,379,0,"*"],[826,10,0,380,0,"*"],[827,53,0,381,0,"*"],[828,83,0,382,0,"*"],[830,92,0,384,0,"*"],[832,392,0,93,1,"FL2MODEL"],[833,394,0,86,0,"MODEL"],[834,395,0,86,1,"PULIDFLUX"],[838,389,0,52,1,"STYLE_MODEL"],[839,388,0,8,1,"VAE"],[840,387,0,52,2,"CLIP_VISION"],[871,371,0,406,0,"IMAGE"],[987,116,0,509,0,"IMAGE"],[995,509,2,518,0,"STRING"],[996,399,0,518,1,"STRING"],[998,518,0,519,0,"*"],[999,519,0,520,1,"STRING"],[1000,398,0,520,0,"CLIP"],[1001,520,0,52,0,"CONDITIONING"],[1002,510,0,521,0,"*"],[1003,522,0,509,1,"FL2MODEL"]],"groups":[{"id":14,"title":"Image01","bounding":[-1842.0230712890625,-464.0518798828125,4848.611328125,937.0343627929688],"color":"#3f789e","font_size":100,"flags":{}},{"id":1,"title":"PuLID Face","bounding":[-801.7770385742188,-311.5599670410156,1084.1234130859375,752.1817016601562],"color":"#3f789e","font_size":50,"flags":{}},{"id":2,"title":"image01 - input/output","bounding":[-1832.0230712890625,-314.0517883300781,1012.3861083984375,747.971435546875],"color":"#3f789e","font_size":50,"flags":{}},{"id":3,"title":"Model","bounding":[-3252.500732421875,-555.1611328125,1127.1710205078125,1461.3382568359375],"color":"#b58b2a","font_size":100,"flags":{}},{"id":4,"title":"Image01_generation","bounding":[310.0893249511719,-303.5405578613281,1628.9591064453125,760.1669311523438],"color":"#3f789e","font_size":50,"flags":{}},{"id":22,"title":"RMBG_image01","bounding":[1976.8468017578125,-294.40386962890625,484.1858825683594,759.1062622070312],"color":"#3f789e","font_size":50,"flags":{}},{"id":44,"title":"Output_01","bounding":[2479.92822265625,-290.87115478515625,511.677978515625,754.6962890625],"color":"#3f789e","font_size":50,"flags":{}}],"config":{},"extra":{"ds":{"scale":0.6209213230591565,"offset":[4124.954463713269,47.13540694129701]},"frontendVersion":"1.25.11","links_added_by_ue":[],"ue_links":[],"0246.VERSION":[0,0,4],"VHS_latentpreview":false,"VHS_latentpreviewrate":0,"VHS_MetadataImage":true,"VHS_KeepIntermediate":true},"version":0.4}